base_flex/__init__.py
base_flex/alphabets.py
base_flex/base_flex.py
base_flex/tests/__init__.py
base_flex/tests/test_base_flex.py
base_flex-0.1.0.dist-info/METADATA
base_flex-0.1.0.dist-info/WHEEL
base_flex-0.1.0.dist-info/RECORD
