Metadata-Version: 2.1
Name: base-flex
Version: 0.1.0
Summary: A flexible base-N encoder/decoder implementation supporting standard and custom alphabets
Author: Valerius Mattfeld
Author-email: mail@valerius.me
Requires-Python: >=3.9,<4.0
Classifier: Programming Language :: Python :: 3
Classifier: Programming Language :: Python :: 3.9
Classifier: Programming Language :: Python :: 3.10
Classifier: Programming Language :: Python :: 3.11
Classifier: Programming Language :: Python :: 3.12
Requires-Dist: coverage (>=7.6.10,<8.0.0)
